vae_toolkit/__init__.py
vae_toolkit/image_utils.py
vae_toolkit/model_config.py
vae_toolkit/py.typed
vae_toolkit/vae_loader.py
vae_toolkit-0.1.0.dist-info/licenses/LICENSE
vae_toolkit-0.1.0.dist-info/METADATA
vae_toolkit-0.1.0.dist-info/WHEEL
vae_toolkit-0.1.0.dist-info/top_level.txt
vae_toolkit-0.1.0.dist-info/RECORD
