Metadata-Version: 2.4
Name: vae-toolkit
Version: 0.1.0
Summary: Stable Diffusion VAE toolkit - image processing and model loading utilities
Author-email: Yus314 <shizhaoyoujie@gmail.com>
License: MIT License
Project-URL: Homepage, https://github.com/mdipcit/vae-toolkit
Project-URL: Repository, https://github.com/mdipcit/vae-toolkit
Project-URL: Issues, https://github.com/mdipcit/vae-toolkit/issues
Project-URL: Documentation, https://vae-toolkit.readthedocs.io
Project-URL: Changelog, https://github.com/mdipcit/vae-toolkit/blob/main/CHANGELOG.md
Keywords: vae,stable-diffusion,image-processing,deep-learning,diffusers
Classifier: Development Status :: 4 - Beta
Classifier: Intended Audience :: Developers
Classifier: Intended Audience :: Science/Research
Classifier: License :: OSI Approved :: MIT License
Classifier: Programming Language :: Python :: 3
Classifier: Programming Language :: Python :: 3.8
Classifier: Programming Language :: Python :: 3.9
Classifier: Programming Language :: Python :: 3.10
Classifier: Programming Language :: Python :: 3.11
Classifier: Programming Language :: Python :: 3.12
Classifier: Topic :: Scientific/Engineering :: Artificial Intelligence
Classifier: Topic :: Scientific/Engineering :: Image Processing
Classifier: Topic :: Multimedia :: Graphics
Classifier: Topic :: Multimedia :: Graphics :: Graphics Conversion
Classifier: Operating System :: OS Independent
Requires-Python: >=3.8
License-File: LICENSE
Requires-Dist: torch>=2.0.0
Requires-Dist: torchvision>=0.15.0
Requires-Dist: Pillow>=9.0.0
Requires-Dist: numpy>=1.20.0
Requires-Dist: diffusers>=0.20.0
Provides-Extra: test
Requires-Dist: pytest>=6.0; extra == "test"
Requires-Dist: pytest-cov>=2.10; extra == "test"
Requires-Dist: pytest-mock>=3.6; extra == "test"
Provides-Extra: dev
Requires-Dist: black>=22.0; extra == "dev"
Requires-Dist: flake8>=4.0; extra == "dev"
Requires-Dist: mypy>=0.900; extra == "dev"
Requires-Dist: isort>=5.10; extra == "dev"
Provides-Extra: docs
Requires-Dist: sphinx>=4.0; extra == "docs"
Requires-Dist: sphinx-rtd-theme>=1.0; extra == "docs"
Provides-Extra: all
Requires-Dist: vae-toolkit[dev,docs,test]; extra == "all"
Dynamic: license-file
